{"_ts":[1559358398,1559381020],"_r":{"breakdown":{"html":{"bytes":[7356,7356],"requests":[1,1]},"js":{"bytes":[338434,312490],"requests":[21,21]},"css":{"bytes":[23242,23242],"requests":[3,3]},"image":{"bytes":[80805,74418],"requests":[9,10]},"flash":{"bytes":[0,0],"requests":[0,0]},"font":{"bytes":[0,0],"requests":[0,0]},"video":{"bytes":[0,0],"requests":[0,0]},"other":{"bytes":[5566,5447],"requests":[11,10]}},"date":[1559358398,1559381020],"domElements":[585,584],"domInteractive":[2828,5037],"firstPaint":[2100.7,4490.095000001],"fullyLoaded":[11057,15361],"id":["190601_CF_8e6a1d50a1d661bac90d0bc41cb0c5be","190601_ZN_f40cb44c7e4bbcc74ac15135e62012fb"],"loadTime":[5563,6867],"render":[4400,7700],"SpeedIndex":[6854,9114],"TTFB":[1251,1410],"videoFrames":[[{"_i":"ms_000000.jpg","_t":0,"_vc":0},{"_i":"ms_004400.jpg","_t":4400,"_vc":14},{"_i":"ms_005300.jpg","_t":5300,"_vc":14},{"_i":"ms_005500.jpg","_t":5500,"_vc":18},{"_i":"ms_005600.jpg","_t":5600,"_vc":21},{"_i":"ms_005700.jpg","_t":5700,"_vc":23},{"_i":"ms_005900.jpg","_t":5900,"_vc":23},{"_i":"ms_006000.jpg","_t":6000,"_vc":24},{"_i":"ms_006200.jpg","_t":6200,"_vc":34},{"_i":"ms_006300.jpg","_t":6300,"_vc":34},{"_i":"ms_006600.jpg","_t":6600,"_vc":34},{"_i":"ms_007600.jpg","_t":7600,"_vc":60},{"_i":"ms_007700.jpg","_t":7700,"_vc":100}],[{"_i":"ms_000000.jpg","_t":0,"_vc":0},{"_i":"ms_007700.jpg","_t":7700,"_vc":34},{"_i":"ms_008900.jpg","_t":8900,"_vc":43},{"_i":"ms_009000.jpg","_t":9000,"_vc":43},{"_i":"ms_009100.jpg","_t":9100,"_vc":44},{"_i":"ms_009400.jpg","_t":9400,"_vc":44},{"_i":"ms_009500.jpg","_t":9500,"_vc":80},{"_i":"ms_009700.jpg","_t":9700,"_vc":80},{"_i":"ms_010000.jpg","_t":10000,"_vc":80},{"_i":"ms_010800.jpg","_t":10800,"_vc":88},{"_i":"ms_011000.jpg","_t":11000,"_vc":100}]],"visualComplete":[7700,11000],"lighthouse":[42,69],"pagespeed":[76,77]}}